{
    "texts": [
        {
            "link": "http://sandberg.nl/design/essays/2015/david-juan-ortiz/",
            "title": "Hypnagogia and the colonisation of memory",
            "author": "David Ortiz Juan"
        },
        {
            "link": "http://sandberg.nl/design/essays/2015/isaura-sanwirjatmo/",
            "title": "SoSo Lobi",
            "author": "Isaura Sanwirjatmo"
        },
        {
            "link": "http://sandberg.nl/design/essays/2015/isaura-sanwirjatmo/",
            "title": "To Whom Do I Owe My Body?",
            "author": "Rasmus Svensson"
        },
        {
            "link": "http://sandberg.nl/design/essays/2015/isaura-sanwirjatmo/",
            "title": "Servers and Serfs",
            "author": "Rasmus Svensson"
        },
        {
            "link": "http://sandberg.nl/design/essays/2015/isaura-sanwirjatmo/",
            "title": "Tokens of Decadence",
            "author": "Giada Fiorindi"
        },
        {
            "link": "http://sandberg.nl/design/essays/2015/isaura-sanwirjatmo/",
            "title": "To infinity, and beyond!",
            "author": "Tessel Bruhl"
        },
        {
            "link": "http://sandberg.nl/design/essays/2015/janna-ulrich/",
            "title": "Ideonautics",
            "author": "Janna Ulrich"
        },
        {
            "link": "http://sandberg.nl/design/essays/2015/janna-ulrich/",
            "title": "modernism: or, the optimism",
            "author": "Jaroslav Toussaint"
        },
        {
            "link": "http://sandberg.nl/design/essays/2015/janna-ulrich/",
            "title": "Low EROEI manifesto",
            "author": "Tommi Vasko"
        },
        {
            "link": "http://sandberg.nl/design/essays/2015/janna-ulrich/",
            "title": "Post-Liberation Design",
            "author": "Hannes Bernard"
        },
        {
            "link": "http://sandberg.nl/design/essays/2015/janna-ulrich/",
            "title": "Face Value",
            "author": "Simone C. Niquille"
        }
    ]
}
